pycordrest/__init__.py
pycordrest/rest.py
pycordrest-0.1.0.dist-info/LICENSE
pycordrest-0.1.0.dist-info/WHEEL
pycordrest-0.1.0.dist-info/METADATA
pycordrest-0.1.0.dist-info/RECORD
