Metadata-Version: 2.1
Name: pycordrest
Version: 0.1.0
Summary: The REST API for py-cord
Home-page: https://github.com/InfiniteCore/pycordrest
License: MIT
Keywords: discord,rest
Author: InfiniteCore
Requires-Python: >=3.8,<4.0
Classifier: License :: OSI Approved :: MIT License
Classifier: Programming Language :: Python :: 3
Classifier: Programming Language :: Python :: 3.10
Classifier: Programming Language :: Python :: 3.8
Classifier: Programming Language :: Python :: 3.9
Requires-Dist: Flask (>=2.0.3,<3.0.0)
Requires-Dist: py-cord (>=1.7.3,<2.0.0)
Project-URL: Repository, https://github.com/InfiniteCore/pycordrest
